edifice/__init__.py
edifice/__main__.py
edifice/app.py
edifice/engine.py
edifice/hooks.py
edifice/logger.py
edifice/run_subprocess_with_callback.py
edifice/runner.py
edifice/utilities.py
edifice/base_components/__init__.py
edifice/base_components/base_components.py
edifice/base_components/button_view.py
edifice/base_components/check_box.py
edifice/base_components/flow_view.py
edifice/base_components/image_aspect.py
edifice/base_components/radio_button.py
edifice/base_components/scroll_bar.py
edifice/base_components/spin_input.py
edifice/base_components/table_grid_view.py
edifice/extra/__init__.py
edifice/extra/matplotlib_figure.py
edifice/extra/numpy_image.py
edifice/extra/pyqtgraph_plot.py
edifice/icons/__init__.py
edifice/icons/font-awesome/regular/address-book.svg
edifice/icons/font-awesome/regular/address-card.svg
edifice/icons/font-awesome/regular/angry.svg
edifice/icons/font-awesome/regular/arrow-alt-circle-down.svg
edifice/icons/font-awesome/regular/arrow-alt-circle-left.svg
edifice/icons/font-awesome/regular/arrow-alt-circle-right.svg
edifice/icons/font-awesome/regular/arrow-alt-circle-up.svg
edifice/icons/font-awesome/regular/bell-slash.svg
edifice/icons/font-awesome/regular/bell.svg
edifice/icons/font-awesome/regular/bookmark.svg
edifice/icons/font-awesome/regular/building.svg
edifice/icons/font-awesome/regular/calendar-alt.svg
edifice/icons/font-awesome/regular/calendar-check.svg
edifice/icons/font-awesome/regular/calendar-minus.svg
edifice/icons/font-awesome/regular/calendar-plus.svg
edifice/icons/font-awesome/regular/calendar-times.svg
edifice/icons/font-awesome/regular/calendar.svg
edifice/icons/font-awesome/regular/caret-square-down.svg
edifice/icons/font-awesome/regular/caret-square-left.svg
edifice/icons/font-awesome/regular/caret-square-right.svg
edifice/icons/font-awesome/regular/caret-square-up.svg
edifice/icons/font-awesome/regular/chart-bar.svg
edifice/icons/font-awesome/regular/check-circle.svg
pyedifice-4.4.1.dist-info/METADATA
pyedifice-4.4.1.dist-info/WHEEL
pyedifice-4.4.1.dist-info/top_level.txt
pyedifice-4.4.1.dist-info/RECORD
