Metadata-Version: 2.4
Name: pyedifice
Version: 4.4.1
Summary: Declarative GUI framework for Python and Qt
Author: David Ding, James D. Brock, Viktor Kronvall
License: MIT License
Project-URL: Homepage, https://pyedifice.github.io
Project-URL: Repository, https://github.com/pyedifice/pyedifice
Classifier: Topic :: Software Development :: User Interfaces
Requires-Python: >=3.10
Requires-Dist: qasync>=0.26.0
Requires-Dist: typing-extensions>=4.0.0
Provides-Extra: pyside6-essentials
Requires-Dist: PySide6-Essentials>=6.0.0; extra == "pyside6-essentials"
Provides-Extra: pyqt6
Requires-Dist: PyQt6>=6.0.0; extra == "pyqt6"
